quiltcore/__init__.py
quiltcore/builder.py
quiltcore/config/config.py
quiltcore/config/data.py
quiltcore/config/quiltcore.yaml
quiltcore/config/quiltspec.yaml
quiltcore/config/spec.py
quiltcore/config/udi.py
quiltcore/domain.py
quiltcore/entry.py
quiltcore/factory.py
quiltcore/manifest.py
quiltcore/namespace.py
quiltcore/py.typed
quiltcore/scheme.py
quiltcore/table3.py
quiltcore/table4.py
quiltcore/udg/README.md
quiltcore/udg/child.py
quiltcore/udg/codec.py
quiltcore/udg/folder.py
quiltcore/udg/header.py
quiltcore/udg/keyed.py
quiltcore/udg/node.py
quiltcore/udg/root.py
quiltcore/udg/tabular.py
quiltcore/udg/types.py
quiltcore/udg/verifiable.py
quiltcore-0.6.3.dist-info/LICENSE
quiltcore-0.6.3.dist-info/METADATA
quiltcore-0.6.3.dist-info/WHEEL
quiltcore-0.6.3.dist-info/RECORD
