Metadata-Version: 2.1
Name: quiltcore
Version: 0.6.3
Summary: low-level plubming to read/write Quilt packages
Author: Ernest Prabhakar
Author-email: ernest@quiltdata.io
Requires-Python: >=3.10,<4.0
Classifier: Programming Language :: Python :: 3
Classifier: Programming Language :: Python :: 3.10
Classifier: Programming Language :: Python :: 3.11
Classifier: Programming Language :: Python :: 3.12
Requires-Dist: jsonlines (==1.2.0)
Requires-Dist: multiformats (>=0.2.1,<0.3.0)
Requires-Dist: pandas (>=2.0.2,<3.0.0)
Requires-Dist: pandas-stubs (>=2.0.2.230605,<3.0.0.0)
Requires-Dist: pyarrow (>=14.0.0,<15.0.0)
Requires-Dist: quilt3 (>=5.3.1,<6.0.0)
Requires-Dist: s3fs (>=2023.6.0,<2024.0.0)
Requires-Dist: typing-extensions (>=4.6.3,<5.0.0)
Requires-Dist: tzlocal (>=5.0.1,<6.0.0)
Requires-Dist: un-yaml (>=0.3.1)
Requires-Dist: universal-pathlib (>=0.1.3,<0.2.0)
